.gitignore
LICENSE
README.md
pyproject.toml
setup.py
.github/workflows/pypi.yml
.vscode/settings.json
_external/MikkTSpace/README.md
_external/MikkTSpace/mikktspace.c
_external/MikkTSpace/mikktspace.h
src/mikktspace/__init__.py
src/mikktspace/_version.py
src/mikktspace/mikktspace_c/mikktspace.c
src/mikktspace/mikktspace_c/mikktspace.pyx
src/pymikktspace.egg-info/PKG-INFO
src/pymikktspace.egg-info/SOURCES.txt
src/pymikktspace.egg-info/dependency_links.txt
src/pymikktspace.egg-info/top_level.txt
tests/test_gltf.py