Metadata-Version: 2.1
Name: pymikktspace
Version: 0.3.0
Summary: mikktspace
Home-page: https://github.com/ousttrue/pymikktspace
Author: ousttrue
Author-email: ousttrue@gmail.com
License: UNKNOWN
Platform: UNKNOWN
License-File: LICENSE
